[
    {
        "Gestion": [
            {
                "title": "PROJET DE CREATION D'UNE UNITE DE TRANSFORMATION D'OVAHO EN HUILE ALIMENTAIRE A FORT-DAUPHIN",
                "path": "rakotoariveloj_ges_m1_07.pdf",
                "author": "RAKOTOARIVELO Judex",
                "date": "06/09/2007",
                "lieu": "Université d'antananarivo",
                "type": "Memoire de fin d'études"
            },
            {
                "title": "AMÉLIORATION DE LA QUALITE DE SERVICES REPONDANT AUX EXIGENCES DE LA CLIENTÈLE (CAS : AGENCE STAR- TOLIARA)",
                "path": "rakotoarisonLalaPD_GES_M1_09.pdf",
                "author": "Lala Paul Davidson RAKOTOARISON",
                "date": "12/09/2009",
                "lieu": "Université de Toamasina",
                "type": "Maitrise"
            },
            {
                "title": "PROJET D’ELEVAGE ET DE COMMERCIALISATION DE PORCIN DANS LA VILLE DE TSIROANOMANDIDY: REGION BONGOLAVA",
                "path": "rakotoarisonHaingoniainaY_GES_M1_07.pdf",
                "author": "RAKOTOARISON Haingonirina Yvonne",
                "date": "09/06/2007",
                "lieu": "Université d'antananarivo",
                "type": "Memoire de fin d'études"
            },
            {
                "title": "PROJET DE CREATION D’UNE UNITE DE PISCICULTURE EN CAGES DANS LA RIVIERE D’ANTSIRIKA, REGION ALAOTRA MANGORO",
                "path": "rajoelinirinasaholimalalaat_ges_m1_07.pdf",
                "author": "RAJOELINIRINA Salohimalala Aina Tahiry",
                "date": "08/09/2007",
                "lieu": "Université d'antananarivo",
                "type": "Memoire de fin d'études"
            },
            {
                "title": "Projet de création d'une unité de restauration et d'hotellerie denomée Marovoay 3 étooiles, sise a Marovoay",
                "path": "rajaoharinesya_ges_m1_07.pdf",
                "author": "RAJAOHARINESY Adolphe",
                "date": "09/09/2007",
                "lieu": "Université d'antananarivo",
                "type": "Maitrise"
            },
            {
                "title": "PROJET DE CREATION D’UN CENTRE INFORMATIQUE DANS LA COMMUNE URBAINE DE MAINTIRANO",
                "path": "rajafetramiorahasina_ges_m1_05.pdf",
                "author": "RAJAFETRA Miora Hasina",
                "date": "20/12/2005",
                "lieu": "Université d'antananarivo",
                "type": "Maitrise"
            },
            {
                "title": "PROJET DE CREATION D’UN CYBERCENTRE DANS LA VILLE DE SAMBAVA",
                "path": "raherinirinavaosoloe_ges_m1_07.pdf",
                "author": "RAHELINIRINA Vaosolo Esthella",
                "date": "09/06/2007",
                "lieu": "Université d'antananarivo",
                "type": "Maitrise"
            },
            {
                "title": "PROJET DE CREATION D’UN MULTI-SERVICE INFORMATIQUE A AMBOSITRA VILLE",
                "path": "rahasindrainyt_ges_m1_05.pdf",
                "author": "RAHASINDRAINY Tsitohaina",
                "date": "23/06/2005",
                "lieu": "Université d'antananarivo",
                "type": "Maitrise"
            },
            {
                "title": "PROJET DE CREATION D’UNE ECOLE DE FORMATION EN COUPE ET COUTURE DANS LE DISTRICT DE TSIROANOMANDIDY.",
                "path": "raharomarotianaJaonaB_GES_M1_09.pdf",
                "author": "RAHARIMAROTIANA Jaona Balisame",
                "date": "17/08/2009",
                "lieu": "Université d'antananarivo",
                "type": "Maitrise"
            },
            {
                "title": "PROJET DE CREATION D’UN CENTRE D’ELEVAGE DE TILAPIA EN ETANG DANS LA ZONE RURALE DE TOAMASINA: Cas d’Antanandava",
                "path": "rahajaharimananaHanitraS_GES_M1_06.pdf",
                "author": "Hanitra Solonirina Victorine RAHAJAHARIMANANA",
                "date": "13/12/2006",
                "lieu": "Université de Toamasina",
                "type": "Maitrise"
            },
            {
                "title": "Projet de construction de parking à étage dans la ville d’Antaninarenina",
                "path": "radimilahyTantelyA_GES_MAST_20.pdf",
                "author": "RADIMILAHY Tantely Ambinintsoa",
                "date": "11/12/2019",
                "lieu": "Université d'antananarivo",
                "type": "Master 2"
            },
            {
                "title": "PROJET DE CREATION ET D’EXPLOITATION D’UN COMPLEXE HOTELIER SIS A ANTSIRANANA",
                "path": "rabemanantsoaAndriamihajaT_GES_M1_05.pdf",
                "author": "RABEMANANTSOA Andriamihaja Toky",
                "date": "13/12/2005",
                "lieu": "Université d'antananarivo",
                "type": "Maitrise"
            },
            {
                "title": "REVITALISATION DE L’IMAGE DE MADACOM, client de l’agence Factories Mc Cann, AUPRES DES JEUNES",
                "path": "rabehanitrinionya_ges_m1_05.pdf",
                "author": "RABEHANITRINIONY Aina",
                "date": "12/08/2005",
                "lieu": "Université d'antananarivo",
                "type": "Maitrise"
            },
            {
                "title": "Mise en place d'un institution de crédir bail dans la commune d'ambohidratrimo",
                "path": "rabefitiamv_ges_m1_08.pdf",
                "author": "RABEFITIA Miorasoa Valérie",
                "date": "28/11/2008",
                "lieu": "Université d'antananarivo",
                "type": "Maitrise"
            },
            {
                "title": "PROJET DE CRÉATION D’UNE FORMATION TECHNIQUE ET PROFESSIONNELLE DANS LA RẾGION ALAOTRA MANGORO (Cas du district d’Amparafaravola)",
                "path": "rabearimananaHantavolonaS_GES_M1_10.pdf",
                "author": "RABEARIMANANA Hantavololona Sophie",
                "date": "25/09/2010",
                "lieu": "Université de Toamasina",
                "type": "Maitrise"
            },
            {
                "title": "PROJET DE CREATION D’UNE UNITE DE PORCICULTURE DENOMME UPCP sise à Lazaina SABOTSY NAMEHANA",
                "path": "rabarioelinaMbola L_GES_M1_06.pdf",
                "author": "RABARIOELINA Mbola Lanto",
                "date": "29/12/2006",
                "lieu": "Université d'antananarivo",
                "type": "Maitrise"
            },
            {
                "title": "Projet de création d'un complexe hotelier sise a ranomafana",
                "path": "nambininaChristianaJ_GES_M1_06.pdf",
                "author": "NAMBININA Christiana Judith",
                "date": "05/08/2006",
                "lieu": "Université d'antananarivo",
                "type": "Maitrise"
            },
            {
                "title": "PROJET DE CRÉATION D’UNE UNITÉ DE FABRICATION D’HUILE ESSENTIELLE DE VÉTIVER DANS LE DISTRICT: D’AMBANJA, D’AMBANJA REGION DIANA",
                "path": "naboakaSoaF_GES_M1_11.pdf",
                "author": "Soa Fahouzathe NABOAKA",
                "date": "31/03/2011",
                "lieu": "Université de Toamasina",
                "type": "Maitrise"
            },
            {
                "title": "STRATÉGIES D’AMÉLIORATION DU SECTEUR TRANSIT-IMPORT DE LA SOCIÉTÉ AUXILLIAIRE MARITIME DE MADAGASCAR (CAS DE AUXIMAD TOAMASINA)",
                "path": "moyneAshleyC_GES_M1_12.pdf",
                "author": "Ashley Celestina MOYNE",
                "date": "14/03/2012",
                "lieu": "Université de Toamasina",
                "type": "Maitrise"
            },
            {
                "title": "La gestion de rémunération du personnel - cas de la SIB",
                "path": "mevaAurelien_IUGM_DTS_11.pdf",
                "author": "MEVA Aurélien & RAMADIHANITRA Arisoa Dalia Rosalie",
                "date": "01/03/2011",
                "lieu": "Université de Mahajanga",
                "type": "DTS (DIplôme de Téchnicien Supérieur)"
            },
            {
                "title": "Projet de création d’une unité de production de pisciculture en cage dans la Région Ampefy",
                "path": "lalaoarivelove_ges_m1_07.pdf",
                "author": "LALAOARIVELO VONINOLIVA Evanindraina",
                "date": "27/09/2007",
                "lieu": "Université d'antananarivo",
                "type": "Mémoire de fin d'étude"
            },
            {
                "title": "Analyse de la gestion de tresorerie de la société Hasy Malagasy (HASYMA)",
                "path": "lalahisoaRalevasonA_GES_M1_2000.pdf",
                "author": "LALAHISOA Ralevason Axel",
                "date": "05/05/2000",
                "lieu": "Université d'antananarivo",
                "type": "Mémoire de fin d'étude"
            },
            {
                "title": "PROJET DE CREATION D’UN CENTRE INFORMATIQUE A AMBOHIPO",
                "path": "koerarn_ges_m1_04.pdf",
                "author": "KOERA Ravelonarivo Natanaël",
                "date": "11/05/2004",
                "lieu": "Université d'antananarivo",
                "type": "Maitrise"
            },
            {
                "title": "Projet d'implantation d'écolodge près du parc national Marojejy (SAVA)",
                "path": "jobyjs_ges_m1_08.pdf",
                "author": "JOBY Jean Sacha",
                "date": "11/08/2008",
                "lieu": "Université d'antananarivo",
                "type": "Maitrise"
            },
            {
                "title": "LA VALORISATION DU PERSONNEL PAR LA GESTION DE LA REMUNERATION: CAS DE LA MAISON DES PAYSANS TOLIARA",
                "path": "jeanneMarieRPV_GES_M1_10.pdf",
                "author": "JEANNE-MARIE MARIE Ralaivelo Pauline Volanera",
                "date": "01/08/2010",
                "lieu": "Université de Toliara",
                "type": "Maitrise"
            },
            {
                "title": "LA GESTION COMPTABLE DE LA SOCIETE AUXIMAX : « Analyse et Proposition d’Amélioration »",
                "path": "herinaivoNoelisonE_GES_M1_06.pdf",
                "author": "HERINAIVO Noëlson Elisé",
                "date": "18/12/2006",
                "lieu": "Université d'antananarivo",
                "type": "Maitrise"
            },
            {
                "title": "PROJET DE CREATION D’UNE MICRO EDITION DENOMMEE PARAF CYBER SIS A FARAFANGANA VILLE",
                "path": "heldaColombeN_GES_M1_10.pdf",
                "author": "HELDA COLOMBE NABE",
                "date": "17/11/2010",
                "lieu": "Université d'antananarivo",
                "type": "Maitrise"
            },
            {
                "title": "Projet de création d'un tour opérateur",
                "path": "andriamboavonjyMampionintsoaER_GES_M1_07.pdf",
                "author": "ANDRIAMBOAVONJY Mampionintsoa Evah R.",
                "date": "11/12/2007",
                "lieu": "Université d'antananarivo",
                "type": "Maitrise"
            },
            {
                "title": "PROJET DE CREATION D’UNE SOCIETE DE TRANSPORT DESSERVANT LA ZONE SUD DE MADAGASCAR",
                "path": "andriamiradoi_ges_m1_06.pdf",
                "author": "ANDRIAMIRADO Irina",
                "date": "01/07/2006",
                "lieu": "Université d'antananarivo",
                "type": "Maitrise"
            },
            {
                "title": "PROJET D’IMPLANTATION D’UNE ENTREPRISE DE PRODUCTION ET DE VENTE DES MEUBLES EN BOIS COLORES A ANTANANARIVO",
                "path": "andriamirilalaDera_GES_MAST_18.pdf",
                "author": "ANDRIAMIRILALA Dera",
                "date": "05/12/2018",
                "lieu": "Université d'antananarivo",
                "type": "Master 2"
            },
            {
                "title": "PROJET DE CREATION D'UNE UNITE D'ELEVAGE PORCIN DANS LA CIOMMUNE DE SOAMAHAMANINA",
                "path": "andrianaivol_ges_m1_07.pdf",
                "author": "Andrianaivo Lalasoa",
                "date": "17/12/2007",
                "lieu": "Université d'antananarivo",
                "type": "Maitrise"
            },
            {
                "title": "PROJET DE PRODUCTION D’ETHANOL A PARTIR DE LA FARINE DE MANIOC, DANS LE DISTRICT DE MAEVATANANA, REGION BETSIBOKA",
                "path": "andrianantenainatbe_ges_m1_08.pdf",
                "author": "ANDRIANANTENAINA TANTELINIAINA BERSON EDINAH",
                "date": "11/08/2008",
                "lieu": "Université d'antananarivo",
                "type": "Maitrise"
            },
            {
                "title": "PROJET D’EXTENSION D’UNE ENTREPRISE DE PRODUCTION AUDIOVISUELLE CAS DE TURBO IMAGE PRODUCTION (TIPR)",
                "path": "andrianoavyyl_ges_m1_04.pdf",
                "author": "ANDRIANOAVY Yvan Lantoharimamy",
                "date": "02/12/2004",
                "lieu": "Université d'antananarivo",
                "type": "Maitrise"
            },
            {
                "title": "AMÉLIORATION DU SYSTÈME DE GESTION DES PLANTEURS SEMI-INDUSTRIELS DE LA SOCTAM",
                "path": "andriantsaraTodisoaKG_IIUGM_Lic_11.pdf",
                "author": "ANDRIANTSARA Todisoa Kamal Gérard",
                "date": "03/03/2011",
                "lieu": "Université de Mahajanga",
                "type": "Licence"
            },
            {
                "title": "MISE EN PLACE D’UNE STATION RADIOPHONIQUE ET D’UNE TÉLÉVISION PRIVÉES DANS LA RÉGION SOFIA (CAS DE DISTRICT DE MANDRITSARA)",
                "path": "anjarasonDedyW_GES_M1_11.pdf",
                "author": "DEDY Willer Anjarason",
                "date": "22/08/2011",
                "lieu": "Université de Toamasina",
                "type": "Maitrise"
            },
            {
                "title": "CREATION D’ENTREPRISE D’EXPORTATION DE CAFE ET CACAO",
                "path": "apolinaireFanivana_GES_MAST_16.pdf",
                "author": "APOLINAIRE FANIVANA",
                "date": "01/07/2016",
                "lieu": "Université de Toamasina",
                "type": "Master 2"
            },
            {
                "title": "ANALYSE SOCIO-ECONOMIQUE DES RISQUES LIES A LA DEFORESTATION (Cas des Aires Protégées de la Montagne d’Ambre, Commune Rurale de Joffre Ville, District d’Antsiranana II, Région de DIANA)",
                "path":"belahyFortuneA_ECO_MAST_15.pdf",
                "author": "BELAHY Fortuné André",
                "date": "07/09/2015",
                "lieu": "Université d'antananarivo",
                "type": "Master 2"
            },
            {
                "title": "AXIUS MAHAJANGA FACE AU MARCHE LOCAL DES MATERIELS INFORMATIQUES",
                "path": "cossinJosetteMarieT_IUGM_Lic_10.pdf",
                "author": "COSSIN Josette Marie Thérèse & RABEARIVONY Miandrisoa Yolande",
                "date": "11/02/2010",
                "lieu": "Université de Mahajanga",
                "type": "Licence"
            }
        ]
    }
]